collectionish/__init__.py
collectionish/_ancestor_chain_map.py
collectionish/_attydict.py
collectionish/_numdict.py
collectionish/_sentry.py
collectionish/_uniquetuple.py
collectionish/ops.py
collectionish/py.typed
collectionish/utils.py
collectionish-0.5.0.dist-info/AUTHORS.md
collectionish-0.5.0.dist-info/LICENSE
collectionish-0.5.0.dist-info/METADATA
collectionish-0.5.0.dist-info/WHEEL
collectionish-0.5.0.dist-info/top_level.txt
collectionish-0.5.0.dist-info/RECORD
