Metadata-Version: 2.1
Name: collectionish
Version: 0.5.0
Summary: Collectionish is a pure python library extending the basic collection data types and operations for working with them.
Home-page: https://github.com/leaprovenzano/collectionish
Author: Lea Provenzano
Author-email: leaprovenzano@gmail.com
License: MIT license
Keywords: collectionish
Platform: UNKNOWN
Classifier: Development Status :: 2 - Pre-Alpha
Classifier: Intended Audience :: Developers
Classifier: License :: OSI Approved :: MIT License
Classifier: Natural Language :: English
Classifier: Programming Language :: Python :: 3
Classifier: Programming Language :: Python :: 3.7
Classifier: Programming Language :: Python :: 3.8
Classifier: Programming Language :: Python :: 3.9
Classifier: Programming Language :: Python :: 3 :: Only
